LICENSE
MANIFEST.in
README.md
pyproject.toml
setup.py
crings/crings.cpp
crings/crings.pyx
external/frame_msgs/__init__.py
external/frame_msgs/msg/_DetectedPerson.py
external/frame_msgs/msg/_DetectedPersons.py
external/frame_msgs/msg/_PersonTrajectories.py
external/frame_msgs/msg/_PersonTrajectory.py
external/frame_msgs/msg/_PersonTrajectoryEntry.py
external/frame_msgs/msg/_TrackedPerson.py
external/frame_msgs/msg/_TrackedPerson2d.py
external/frame_msgs/msg/_TrackedPersons.py
external/frame_msgs/msg/_TrackedPersons2d.py
external/frame_msgs/msg/__init__.py
external/tf_bag/__init__.py
navrep/__init__.py
navrep.egg-info/PKG-INFO
navrep.egg-info/SOURCES.txt
navrep.egg-info/dependency_links.txt
navrep.egg-info/requires.txt
navrep.egg-info/top_level.txt
navrep/envs/__init__.py
navrep/envs/archiveenv.py
navrep/envs/cadrlenv.py
navrep/envs/dreamenv.py
navrep/envs/e2eenv.py
navrep/envs/encodedenv.py
navrep/envs/ianenv.py
navrep/envs/imdreamenv.py
navrep/envs/jointenv.py
navrep/envs/markencodedenv.py
navrep/envs/markenv.py
navrep/envs/markonedreamenv.py
navrep/envs/marktwodreamenv.py
navrep/envs/navreptrainencodedenv.py
navrep/envs/navreptrainenv.py
navrep/envs/scenario_list.py
navrep/envs/toydreamenv.py
navrep/envs/toyenv.py
navrep/envs/toytcndreamenv.py
navrep/models/__init__.py
navrep/models/gpt.py
navrep/models/gpt1d.py
navrep/models/rnn.py
navrep/models/siren1d.py
navrep/models/tcn.py
navrep/models/tinyvae.py
navrep/models/torchvae.py
navrep/models/vae1d.py
navrep/models/vae1dlstm.py
navrep/models/vae2d.py
navrep/models/vaelstm.py
navrep/scripts/__init__.py
navrep/scripts/check_imrnn.py
navrep/scripts/check_rnn.py
navrep/scripts/check_siren1d.py
navrep/scripts/check_tcn.py
navrep/scripts/check_vae.py
navrep/scripts/check_vae1d.py
navrep/scripts/cross_test_e2e1dnavreptrain_in_ianenv.py
navrep/scripts/cross_test_e2enavreptrain_in_ianenv.py
navrep/scripts/cross_test_guldenring_in_ianenv.py
navrep/scripts/cross_test_lucia_in_ianenv.py
navrep/scripts/cross_test_navreptrain_in_ianenv.py
navrep/scripts/make_1drnn_dataset.py
navrep/scripts/make_imrnn_dataset.py
navrep/scripts/make_rnn_dataset.py
