Metadata-Version: 1.2
Name: navrep
Version: 0.0.13
Summary: navigation representations
Home-page: UNKNOWN
Author: Daniel Dugas
License: UNKNOWN
Platform: UNKNOWN
Requires-Python: >=3.6, <3.7
